diaryllm/__init__.py
diaryllm-0.1.0.dist-info/licenses/LICENSE
diaryllm-0.1.0.dist-info/METADATA
diaryllm-0.1.0.dist-info/WHEEL
diaryllm-0.1.0.dist-info/top_level.txt
diaryllm-0.1.0.dist-info/RECORD
