Metadata-Version: 2.4
Name: diaryllm
Version: 0.1.0
Summary: Personal Journaling and Diary Management for Large Language Models
Author-email: Laurent-Philippe Albou <lpalbou@gmail.com>
Maintainer-email: Laurent-Philippe Albou <lpalbou@gmail.com>
Project-URL: Homepage, https://github.com/laurent-philippe-albou/diaryllm
Project-URL: Documentation, https://diaryllm.readthedocs.io
Project-URL: Repository, https://github.com/laurent-philippe-albou/diaryllm
Project-URL: Issues, https://github.com/laurent-philippe-albou/diaryllm/issues
Project-URL: Changelog, https://github.com/laurent-philippe-albou/diaryllm/blob/main/CHANGELOG.md
Keywords: llm,diary,journal,personal,ai,chatbot,conversation,memory,relationship
Classifier: Development Status :: 3 - Alpha
Classifier: Intended Audience :: Developers
Classifier: License :: OSI Approved :: MIT License
Classifier: Programming Language :: Python :: 3
Classifier: Programming Language :: Python :: 3.8
Classifier: Programming Language :: Python :: 3.9
Classifier: Programming Language :: Python :: 3.10
Classifier: Programming Language :: Python :: 3.11
Classifier: Programming Language :: Python :: 3.12
Classifier: Topic :: Scientific/Engineering :: Artificial Intelligence
Classifier: Topic :: Software Development :: Libraries :: Python Modules
Classifier: Topic :: Text Processing :: Linguistic
Classifier: Topic :: Communications :: Chat
Requires-Python: >=3.8
License-File: LICENSE
Requires-Dist: typing-extensions>=4.0.0
Provides-Extra: dev
Requires-Dist: pytest>=7.0.0; extra == "dev"
Requires-Dist: pytest-cov>=4.0.0; extra == "dev"
Requires-Dist: black>=22.0.0; extra == "dev"
Requires-Dist: isort>=5.10.0; extra == "dev"
Requires-Dist: flake8>=5.0.0; extra == "dev"
Requires-Dist: mypy>=1.0.0; extra == "dev"
Provides-Extra: vector
Requires-Dist: chromadb>=0.4.0; extra == "vector"
Requires-Dist: sentence-transformers>=2.0.0; extra == "vector"
Provides-Extra: full
Requires-Dist: chromadb>=0.4.0; extra == "full"
Requires-Dist: sentence-transformers>=2.0.0; extra == "full"
Requires-Dist: sqlalchemy>=1.4.0; extra == "full"
Requires-Dist: pydantic>=2.0.0; extra == "full"
Dynamic: license-file
